flick_sdk/__init__.py
flick_sdk/test.py
flick_sdk-0.0.1.dist-info/LICENCE.txt
flick_sdk-0.0.1.dist-info/METADATA
flick_sdk-0.0.1.dist-info/WHEEL
flick_sdk-0.0.1.dist-info/top_level.txt
flick_sdk-0.0.1.dist-info/RECORD
