Metadata-Version: 2.1
Name: flick_sdk
Version: 0.0.1
Summary: Flick Python SDK
Author: Quraba inc
License-File: LICENCE.txt
